LICENSE.txt
MANIFEST.in
README.rst
ets.py
ets_docs.py
setup.py
setup_data.py
docs/Makefile
docs/source/conf.py
docs/source/index.rst
docs/source/_static/default.css
docs/source/_static/e-logo-rev.png
docs/source/_static/et.ico
ets.egg-info/PKG-INFO
ets.egg-info/SOURCES.txt
ets.egg-info/dependency_links.txt
ets.egg-info/entry_points.txt
ets.egg-info/requires.txt
ets.egg-info/top_level.txt