Metadata-Version: 1.1
Name: ets
Version: 4.4.2
Summary: Enthought Tool Suite meta-project
Home-page: http://code.enthought.com/projects/tool-suite.php
Author: ETS Developers
Author-email: enthought-dev@enthought.com
License: BSD
Download-URL: http://www.enthought.com/repo/ets/ets-4.4.2.tar.gz
Platform: Windows
Platform: Linux
Platform: Mac OS-X
Platform: Unix
Platform: Solaris
Classifier: Development Status :: 4 - Beta
Classifier: Intended Audience :: Developers
Classifier: Intended Audience :: Science/Research
Classifier: License :: OSI Approved :: BSD License
Classifier: Operating System :: MacOS
Classifier: Operating System :: Microsoft :: Windows
Classifier: Operating System :: OS Independent
Classifier: Operating System :: POSIX
Classifier: Operating System :: Unix
Classifier: Programming Language :: Python
Classifier: Topic :: Scientific/Engineering
Classifier: Topic :: Software Development
Classifier: Topic :: Software Development :: Libraries
